pictl/__init__.py
pictl/cli/__init__.py
pictl/cli/main.py
pictl/config/__init__.py
pictl/config/config.py
pictl/config/regions.py
pictl/pic/__init__.py
pictl/pic/pic.py
pictl/upload/__init__.py
pictl/upload/upload.py
pictl/utils/__init__.py
pictl/utils/utils.py
pictl-0.3.0.dist-info/LICENSE
pictl-0.3.0.dist-info/METADATA
pictl-0.3.0.dist-info/WHEEL
pictl-0.3.0.dist-info/entry_points.txt
pictl-0.3.0.dist-info/RECORD
