Metadata-Version: 2.1
Name: pictl
Version: 0.3.0
Summary: A command line tool for image processing and uploading (ex. S3-type)
License: MIT
Author: zhonger
Author-email: zhonger@live.cn
Requires-Python: >=3.10,<4.0
Classifier: License :: OSI Approved :: MIT License
Classifier: Programming Language :: Python :: 3
Classifier: Programming Language :: Python :: 3.10
Classifier: Programming Language :: Python :: 3.11
Requires-Dist: Pillow (>=9.3.0,<10.0.0)
Requires-Dist: boto3 (>=1.26.146,<2.0.0)
Requires-Dist: click (>=8.1.3,<9.0.0)
Requires-Dist: inquirer (>=3.1.3,<4.0.0)
Requires-Dist: rich (>=13.4.1,<14.0.0)
Requires-Dist: tomlkit (>=0.11.8,<0.12.0)
